LICENSE.txt
README.md
setup.cfg
setup.py
kex/__init__.py
kex/_get_algorithm.py
kex/_get_dataset.py
kex/_phrase_constructor.py
kex/_stopwords.py
kex/baseline.py
kex/graph_text_rank.py
kex/graph_topic_rank.py
kex/graph_tpr.py
kex/lda.py
kex/lexical_specificity.py
kex/tfidf.py
kex.egg-info/PKG-INFO
kex.egg-info/SOURCES.txt
kex.egg-info/dependency_links.txt
kex.egg-info/requires.txt
kex.egg-info/top_level.txt