Metadata-Version: 2.1
Name: kex
Version: 2.0.6
Summary: Light/easy keyword extraction from documents.
Home-page: https://github.com/asahi417/kex
Author: Asahi Ushio
Author-email: asahi1992ushio@gmail.com
License: MIT
Download-URL: https://github.com/asahi417/kex/archive/v2.0.6.tar.gz
Keywords: keyword-extraction,nlp,information-retrieval
Platform: UNKNOWN
Classifier: Development Status :: 4 - Beta
Classifier: Intended Audience :: Developers
Classifier: Intended Audience :: Science/Research
Classifier: Topic :: Scientific/Engineering
Classifier: License :: OSI Approved :: MIT License
Classifier: Programming Language :: Python :: 3
Requires-Python: >=3.6
License-File: LICENSE.txt
